wacpy/__init__.py
wacpy/types/__init__.py
wacpy/types/message/__init__.py
wacpy/types/message/message.py
wacpy/types/message/contact/__init__.py
wacpy/types/message/contact/contact.py
wacpy/types/message/contact/address/__init__.py
wacpy/types/message/contact/address/address.py
wacpy/types/message/contact/email/__init__.py
wacpy/types/message/contact/email/email.py
wacpy/types/message/contact/name/__init__.py
wacpy/types/message/contact/name/name.py
wacpy/types/message/contact/organization/__init__.py
wacpy/types/message/contact/organization/organization.py
wacpy/types/message/contact/phone/__init__.py
wacpy/types/message/contact/phone/phone.py
wacpy/types/message/contact/url/__init__.py
wacpy/types/message/contact/url/url.py
wacpy/types/message/context/__init__.py
wacpy/types/message/context/context.py
wacpy/types/message/interactive/__init__.py
wacpy/types/message/interactive/interactive.py
wacpy/types/message/interactive/action/__init__.py
wacpy/types/message/interactive/action/action.py
wacpy/types/message/interactive/action/button/__init__.py
wacpy/types/message/interactive/action/button/button.py
wacpy/types/message/interactive/action/button/reply/__init__.py
wacpy/types/message/interactive/action/button/reply/reply.py
wacpy/types/message/interactive/action/section/__init__.py
wacpy/types/message/interactive/action/section/section.py
wacpy/types/message/interactive/action/section/product/__init__.py
wacpy/types/message/interactive/action/section/product/product.py
wacpy/types/message/interactive/action/section/row/__init__.py
wacpy/types/message/interactive/action/section/row/row.py
wacpy/types/message/interactive/body/__init__.py
wacpy/types/message/interactive/body/body.py
wacpy/types/message/interactive/footer/__init__.py
wacpy/types/message/interactive/footer/footer.py
wacpy/types/message/interactive/header/__init__.py
wacpy/types/message/interactive/header/header.py
wacpy/types/message/location/__init__.py
wacpy/types/message/location/location.py
wacpy-0.3.0.dist-info/LICENSE
wacpy-0.3.0.dist-info/METADATA
wacpy-0.3.0.dist-info/WHEEL
wacpy-0.3.0.dist-info/top_level.txt
wacpy-0.3.0.dist-info/RECORD
