Metadata-Version: 2.1
Name: wacpy
Version: 0.3.0
Summary: WhatsApp Cloud API Wrapper
Home-page: https://github.com/Natanel-Shitrit/wacpy
Author: Natanel Shitrit
Author-email: natanelsht@gmail.com
Project-URL: Bug Tracker, https://github.com/Natanel-Shitrit/wacpy/issues
Classifier: Programming Language :: Python :: 3
Classifier: License :: OSI Approved :: GNU General Public License v3 (GPLv3)
Classifier: Operating System :: OS Independent
Requires-Python: >=3.6
License-File: LICENSE
Requires-Dist: requests
Requires-Dist: dataclasses-json
